README.rst
setup.py
py_event/Event.py
py_event/EventActor.py
py_event/EventController.py
py_event/__init__.py
py_event.egg-info/PKG-INFO
py_event.egg-info/SOURCES.txt
py_event.egg-info/dependency_links.txt
py_event.egg-info/top_level.txt