Metadata-Version: 1.1
Name: py-event
Version: 0.0.0
Summary: A single threaded and a run-to-completion event controller
Home-page: https://github.com/SetBased/py-event
Author: Set Based IT Consultancy
Author-email: info@setbased.nl
License: MIT
Keywords: event
Platform: UNKNOWN
Classifier: Development Status :: 3 - Alpha
Classifier: Intended Audience :: Developers
Classifier: License :: OSI Approved :: MIT License
Classifier: Programming Language :: Python :: 3
Classifier: Programming Language :: Python :: 3.6
Classifier: Programming Language :: Python :: 3.7
Classifier: Programming Language :: Python :: 3.8
Classifier: Programming Language :: Python :: 3.9
